py2neo/VERSION
py2neo/__init__.py
py2neo/addressing.py
py2neo/compat.py
py2neo/data.py
py2neo/database.py
py2neo/errors.py
py2neo/matching.py
py2neo/meta.py
py2neo/pep249.py
py2neo/timing.py
py2neo/wiring.py
py2neo/bulk/__init__.py
py2neo/client/__init__.py
py2neo/client/bolt.py
py2neo/client/http.py
py2neo/client/json.py
py2neo/cypher/__init__.py
py2neo/cypher/encoding.py
py2neo/cypher/lexer.py
py2neo/cypher/proc.py
py2neo/cypher/queries.py
py2neo/integration/__init__.py
py2neo/integration/numpy.py
py2neo/integration/pandas.py
py2neo/integration/sympy.py
py2neo/movies/README.md
py2neo/movies/__init__.py
py2neo/movies/movies.ini
py2neo/movies/data/movies.cypher
py2neo/movies/static/camera.png
py2neo/movies/static/main.css
py2neo/movies/views/index.tpl
py2neo/movies/views/movie.tpl
py2neo/movies/views/movie_list.tpl
py2neo/movies/views/person.tpl
py2neo/movies/views/person_list.tpl
py2neo/ogm/__init__.py
py2neo/ogm/models/__init__.py
py2neo/ogm/models/movies.py
py2neo/vendor/__init__.py
py2neo/vendor/bottle.py
py2neoglo4035-2021.2.dev0.dist-info/LICENSE
py2neoglo4035-2021.2.dev0.dist-info/METADATA
py2neoglo4035-2021.2.dev0.dist-info/WHEEL
py2neoglo4035-2021.2.dev0.dist-info/entry_points.txt
py2neoglo4035-2021.2.dev0.dist-info/top_level.txt
py2neoglo4035-2021.2.dev0.dist-info/RECORD
