Metadata-Version: 2.1
Name: py2neoglo4035
Version: 2021.2.dev0
Summary: Python client library and toolkit for Neo4j Unofficial. Used for GLO-4035 ULaval course.
Author: Unofficial
Author-email: david.beauchemin@ift.ulaval.ca
License: Apache License, Version 2.0
Classifier: Development Status :: 6 - Mature
Classifier: Environment :: Console
Classifier: Intended Audience :: Developers
Classifier: Intended Audience :: Information Technology
Classifier: Intended Audience :: Science/Research
Classifier: License :: OSI Approved :: Apache Software License
Classifier: Natural Language :: English
Classifier: Operating System :: OS Independent
Classifier: Programming Language :: Python
Classifier: Programming Language :: Python :: 2
Classifier: Programming Language :: Python :: 2.7
Classifier: Programming Language :: Python :: 3
Classifier: Programming Language :: Python :: 3.5
Classifier: Programming Language :: Python :: 3.6
Classifier: Programming Language :: Python :: 3.7
Classifier: Programming Language :: Python :: 3.8
Classifier: Programming Language :: Python :: 3.9
Classifier: Programming Language :: Python :: Implementation :: CPython
Classifier: Topic :: Database
Classifier: Topic :: Database :: Database Engines/Servers
Classifier: Topic :: Scientific/Engineering
Classifier: Topic :: Software Development
Classifier: Topic :: Software Development :: Libraries
License-File: LICENSE
Requires-Dist: certifi
Requires-Dist: interchange (~=2021.0.4)
Requires-Dist: monotonic
Requires-Dist: packaging
Requires-Dist: pansi (>=2020.7.3)
Requires-Dist: pygments (>=2.0.0)
Requires-Dist: six (>=1.15.0)
Requires-Dist: urllib3
